MANIFEST.in
README.rst
setup.py
pymza/__init__.py
pymza/cli.py
pymza/config.py
pymza/const.py
pymza/container.py
pymza/gevent_helpers.py
pymza/kafka_utils.py
pymza/message.py
pymza/offset.py
pymza/reporting.py
pymza/state.py
pymza/task.py
pymza/utils.py
pymza.egg-info/PKG-INFO
pymza.egg-info/SOURCES.txt
pymza.egg-info/dependency_links.txt
pymza.egg-info/entry_points.txt
pymza.egg-info/requires.txt
pymza.egg-info/top_level.txt
pymza/testing/__init__.py