Metadata-Version: 1.0
Name: pymza
Version: 0.7.18
Summary: Streaming data processing framework inspired by Apache Samza.
Home-page: https://bitbucket.org/rushman/pymza
Author: Sergey Kirillov
Author-email: sergey.kirillov@gmail.com
License: UNKNOWN
Platform: UNKNOWN
